{"ratings": -1, "userreviews": [{"userName": "\u7d2b\u6c34\u6676lujinling", "userReviewDate": "2018-03-17", "userURL": "http://user.17k.com/60264394", "userReview": "\u68a6\u5e7b\u9e8b\u9e7f\u643a<a target='_blank' href='http://www.17k.com/book/2788572.html'>\u300a\u5996\u5b7d\u738b\u7237\u7684\u5e9f\u6750\u5c0f\u738b\u5983\u300b</a>\u6765\u8bbf\uff0c\u8bf7\u591a\u591a\u652f\u6301\uff0c\u6765\u4e2a\u4e2a\u6536\u85cf\u554a\uff01\u795d\u5927\u5927\u65e9\u65e5\u6210\u795e\u3002"}, {"userName": "\u7a7a\u8c37\u7559\u60c5", "userReviewDate": "2018-03-14", "userURL": "http://user.17k.com/45016341", "userReview": "\u4e00\u672c\u597d\u770b\u7684\u4e66<a target='_blank' href='http://www.17k.com/book/2790998.html'>\u300a\u9738\u9053\u4e13\u5c5e\u300b</a>\u6821\u56ed\u603b\u88c1\u957f\u817f\u738b\u5b50\u3001\u9752\u6885\u7af9\u9a6c\u6587<a target='_blank' href='http://www.17k.com/book/2790998.html'>\u300a\u9738\u9053\u4e13\u5c5e\u300b</a>\u524d\u6765\u652f\u6301\uff0c\u559c\u6b22\u7684\u53ef\u4ee5\u6536\u85cf\u8fd8\u6709\u6295\u7968\uff0c\u8c22\u8c22\u3002\u7b80\u4ecb\uff1a\u65bd\u96e8\u7af9\u76ee\u5149\u5446\u6ede\u5730\u770b\u7740\u957f\u817f\u5e05\u54e5\u5149\u7740\u7684\u4e0a\u534a\u8eab\u597d\u534a\u664c\uff0c\u56de\u8fc7\u795e\u6765\u540e\u4f38\u624b\u64e6\u4e86\u64e6\u5634\u89d2\u6839\u672c\u4e0d\u5b58\u5728\u7684\u53e3\u6c34\uff0c\u5979\u662f\u5e94\u8be5\u8d81\u673a\u628a\u5bf9\u65b9\u7684\u4e0a\u8863\u90fd\u8131\u5149\u5462\uff0c\u8fd8\u662f\u5c31\u8fd9\u4e48\u5e2e\u5bf9\u65b9\u64e6\u4e00\u4e0b\u4e0a\u8eab\u7ee7\u7eed\u7a7f\u56de\u53bb\uff1f"}, {"userName": "A\u725b\u9b54\u738b", "userReviewDate": "2018-03-04", "userURL": "http://user.17k.com/56738425", "userReview": "\u597d\u4e66\u9700\u8981\u63a8\u5e7f\uff0c\u6b63\u80fd\u91cf!2018\u63a8\u8350\u4e00\u672c\u597d\u770b\u7684\u4e66<a target='_blank' href='http://www.17k.com/book/2551937.html'>\u300a\u8d85\u65b0\u4eba\u300b</a>\uff0c\u60ca\u9669\u523a\u6fc0\uff0c\u6d6a\u6f2b\u6ee1\u5c4b\uff0c\u70ed\u8840\u683c\u6597\uff0c\u751f\u6b7b\u7231\u604b\uff0c\u6696\u6627\u4e0d\u65ad\uff0c\u5929\u5929\u66f4\u65b0\uff0c\u8bf7\u591a\u5173\u7167\uff0c\u6765\u4e2a\u6536\u85cf\u554a!\uff0c\u70b9\u51fb\u4e66\u540d\u5c31\u53ef\u4ee5\u770b\u5230\u4e66\u4e86\u3002"}, {"userName": "\u4e50\u96c5\u516c\u5b50", "userReviewDate": "2018-03-01", "userURL": "http://user.17k.com/49271610", "userReview": "\u4e3a\u4ec0\u4e48\u6211\u89c9\u5f97\u738b\u7237\u7684\u667a\u5546\u6ca1\u4e5d\u4e5d\u9ad8\u5462\u3002\u54c8\u54c8"}, {"userName": "\u6de1\u7b11\u770b\u4eba\u751f", "userReviewDate": "2018-02-26", "userURL": "http://user.17k.com/45473276", "userReview": "<a target='_blank' href='http://www.17k.com/book/1728734.html'>\u300a\u8d5a\u94b1\u8bb0\u300b</a>\u795d\u5927\u5927\u6b63\u6708\u5341\u4e00\uff0c\u4e00\u5e06\u98ce\u987a\uff0c\u4e00\u7ea2\u5230\u5e95\uff01"}, {"userName": "\u50b2\u5a07\u9b3c459405462", "userReviewDate": "2018-02-26", "userURL": "http://user.17k.com/60120749", "userReview": "\u65b0\u4eba\u633d\u541b\u9752\u4e1d\u643a\u65b0\u4e66<a target='_blank' href='http://www.17k.com/book/2783347.html'>\u300a\u4e5d\u5dde\u6ce3\u51e4\u5f52\u300b</a>\u6765\u8d3a\u4e86[\u73ab\u7470]\u8bf7\u5927\u5bb6\u591a\u591a\u6307\u6559[\u574f\u7b11]"}, {"userName": "A\u725b\u9b54\u738b", "userReviewDate": "2018-02-17", "userURL": "http://user.17k.com/56738425", "userReview": "2018\u63a8\u8350\u4e00\u672c\u597d\u770b\u7684\u4e66<a target='_blank' href='http://www.17k.com/book/2551937.html'>\u300a\u8d85\u65b0\u4eba\u300b</a>\uff0c\u60ca\u9669\u523a\u6fc0\uff0c\u6d6a\u6f2b\u6ee1\u5c4b\uff0c\u70ed\u8840\u683c\u6597\uff0c\u751f\u6b7b\u7231\u604b\uff0c\u6696\u6627\u4e0d\u65ad\uff0c\u5929\u5929\u66f4\u65b0\uff0c\u8bf7\u591a\u5173\u7167\uff0c\u6765\u4e2a\u6536\u85cf\u554a!\uff0c\u70b9\u51fb\u4e66\u540d\u5c31\u53ef\u4ee5\u770b\u5230\u4e66\u4e86\u3002"}, {"userName": "\u4e50\u96c5\u516c\u5b50", "userReviewDate": "2018-02-16", "userURL": "http://user.17k.com/49271610", "userReview": "\u5199\u7740\u5408\u4f5c\u662f\u4ec0\u4e48\u610f\u601d\u5462\uff1f"}, {"userName": "A\u725b\u9b54\u738b", "userReviewDate": "2018-02-15", "userURL": "http://user.17k.com/56738425", "userReview": "\u65b0\u5e74\u5230!\u65b0\u5e74\u5feb\u4e50!\u63a8\u8350\u4e00\u672c\u597d\u770b\u7684\u4e66<a target='_blank' href='http://www.17k.com/book/2551937.html'>\u300a\u8d85\u65b0\u4eba\u300b</a>\uff0c\u60ca\u9669\u523a\u6fc0\uff0c\u6d6a\u6f2b\u6ee1\u5c4b\uff0c\u70ed\u8840\u683c\u6597\uff0c\u751f\u6b7b\u7231\u604b\uff0c\u6696\u6627\u4e0d\u65ad\uff0c\u5929\u5929\u66f4\u65b0\uff0c\u8bf7\u591a\u5173\u7167\uff0c\u6765\u4e2a\u6536\u85cf\u554a!\uff0c\u70b9\u51fb\u4e66\u540d\u5c31\u53ef\u4ee5\u770b\u5230\u4e66\u4e86\u3002"}, {"userName": "\u9ec4\u74dc\u7684\u5bbf\u547d", "userReviewDate": "2018-02-12", "userURL": "http://user.17k.com/53195742", "userReview": "<a target='_blank' href='http://www.17k.com/book/2377865.html'>\u300a\u81f3\u9738\u82cd\u751f\u8bc0\u300b</a>\u6765\u8bbf\uff0c\u6c42\u652f\u6301\u6c42\u6269\u6563\uff0c\u87f9\u87f9\u3002"}, {"userName": "A\u725b\u9b54\u738b", "userReviewDate": "2018-02-10", "userURL": "http://user.17k.com/56738425", "userReview": "\u63a8\u8350\u4e00\u672c\u597d\u770b\u7684\u4e66<a target='_blank' href='http://www.17k.com/book/2551937.html'>\u300a\u8d85\u65b0\u4eba\u300b</a>\uff0c\u60ca\u9669\u523a\u6fc0\uff0c\u6d6a\u6f2b\u6ee1\u5c4b\uff0c\u70ed\u8840\u683c\u6597\uff0c\u751f\u6b7b\u7231\u604b\uff0c\u6696\u6627\u4e0d\u65ad\uff0c\u5929\u5929\u66f4\u65b0\uff0c\u8bf7\u591a\u5173\u7167\uff0c\u6765\u4e2a\u6536\u85cf\u554a!\uff0c\u70b9\u51fb\u4e66\u540d\u5c31\u53ef\u4ee5\u770b\u5230\u4e66\u4e86\u3002"}, {"userName": "17K\u4e66\u53cbw7yq5y6j", "userReviewDate": "2018-02-10", "userURL": "http://user.17k.com/58854041", "userReview": "\u5199\u7684\u5f88\u4e0d\u9519"}, {"userName": "\u5ca9\u6cca", "userReviewDate": "2018-02-07", "userURL": "http://user.17k.com/52703967", "userReview": "<a target='_blank' href='http://www.17k.com/book/2388836.html'>\u300a\u7fa3\u4ed9\u9b54\u5f71\u300b</a>\u6765\u62dc\u8bbf\uff0c\u65b0\u7684\u4e00\u5e74\uff0c\u5927\u5bb6\u5171\u521b\u4f73\u7ee9\uff0c\u575a\u6301\u575a\u6301"}, {"userName": "A\u725b\u9b54\u738b", "userReviewDate": "2018-02-06", "userURL": "http://user.17k.com/56738425", "userReview": "\u63a8\u8350\u4e00\u672c\u597d\u770b\u7684\u4e66<a target='_blank' href='http://www.17k.com/book/2551937.html'>\u300a\u8d85\u65b0\u4eba\u300b</a>\uff0c\u60ca\u9669\u523a\u6fc0\uff0c\u6d6a\u6f2b\u6ee1\u5c4b\uff0c\u6696\u6627\u6e29\u60c5\uff0c\u4f20\u6388\u60c5\u7231\u771f\u8c1b\uff0c\u5929\u5929\u66f4\u65b0\uff0c\u8bf7\u591a\u591a\u5173\u7167\uff0c\u6765\u4e2a\u6536\u85cf\u5427!\u70b9\u51fb\u4e66\u540d\u5c31\u53ef\u4ee5\u770b\u5230\u4e66\u4e86\u3002"}, {"userName": "m\u6728\u7d2b\u503e", "userReviewDate": "2018-02-05", "userURL": "http://user.17k.com/52480433", "userReview": "<a target='_blank' href='http://www.17k.com/book/2751535.html'>\u300a\u8179\u9ed1\u5973\u4eba\u64a9\u7231\u8ba1\u300b</a>\u524d\u6765\u62dc\u8bbf\u5b66\u4e60\uff01\u2196(^\u03c9^)\u2197"}, {"userName": "A\u725b\u9b54\u738b", "userReviewDate": "2018-02-02", "userURL": "http://user.17k.com/56738425", "userReview": "\u63a8\u8350\u4e00\u672c\u60ca\u9669\u523a\u6fc0\u597d\u770b\u7684\u4e66<a target='_blank' href='http://www.17k.com/book/2728167.html'>\u300a\u6211\u548c\u5996\u517d\u6709\u4e2a\u7ea6\u4f1a\u300b</a>\uff0c\u5929\u5929\u66f4\u65b0\uff0c\u8bf7\u591a\u591a\u5173\u7167\uff0c\u6765\u4e2a\u6536\u85cf\u5427!\u70b9\u51fb\u4e66\u540d\u5c31\u53ef\u4ee5\u770b\u5230\u4e86 \u3002"}, {"userName": "17K\u4e66\u53cb20plces9", "userReviewDate": "2018-02-02", "userURL": "http://user.17k.com/59749403", "userReview": "\u6765\u505a\u4e2a\u4efb\u52a1(\u10e6\u5343 3 \u5343\u10e6)"}, {"userName": "kool\u6377", "userReviewDate": "2018-01-28", "userURL": "http://user.17k.com/56730892", "userReview": "\u63a8\u8350\u4e00\u672c\u597d\u770b\u7684\u4e66<a target='_blank' href='http://www.17k.com/book/2551937.html'>\u300a\u8d85\u65b0\u4eba\u300b</a>\uff0c\u60ca\u9669\u523a\u6fc0\uff0c\u6696\u6627\u6d6a\u6f2b\u4e0d\u65ad\uff0c\u5929\u5929\u66f4\u65b0\uff0c\u591a\u591a\u652f\u6301\uff0c\u6765\u4e2a\u6536\u85cf\u3002\u70b9\u51fb\u4e66\u540d\u5c31\u53ef\u4ee5\u770b\u5230\u4e66\u4e86\u3002"}, {"userName": "\u6eaa\u7a97", "userReviewDate": "2018-01-27", "userURL": "http://user.17k.com/58994891", "userReview": "<a target='_blank' href='http://www.17k.com/book/2766057.html'>\u300a\u9526\u95fa\u300b</a>\u6765\u8bbf\uff01\u65b0\u4eba\u4e00\u4e2a\uff0c\u671b\u6276\u6301\uff01"}, {"userName": "A\u725b\u9b54\u738b", "userReviewDate": "2018-01-25", "userURL": "http://user.17k.com/56738425", "userReview": "\u63a8\u8350\u4e00\u672c\u60ca\u9669\u523a\u6fc0\u597d\u770b\u7684\u4e66<a target='_blank' href='http://www.17k.com/book/2728167.html'>\u300a\u6211\u548c\u5996\u517d\u6709\u4e2a\u7ea6\u4f1a\u300b</a>\uff0c\u591a\u591a\u652f\u6301\uff0c\u6765\u4e2a\u6536\u85cf!\u70b9\u51fb\u4e66\u540d\u5c31\u53ef\u4ee5\u770b\u5230\u4e66\u4e86\u3002"}], "description": "\u4e00\u671d\u7a7f\u8d8a\u6210\u5c1a\u4e66\u5343\u91d1\uff0c\u7239\u4e0d\u75bc\u5a18\u4e0d\u7231\uff0c\u8fd8\u8981\u903c\u7740\u5979\u5ac1\u4eba\uff01\u3000\u3000\u542c\u8bf4\u8981\u5ac1\u7684\u662f\u7687\u5e1d\u6700\u5ba0\u7231\u7684\u7687\u5b50\uff1f\u7687\u5b50\u6211\u559c\u6b22\uff0c\u8d22\u5927\u6c14\u7c97\uff01\u3000\u3000\u542c\u8bf4\u8981\u5ac1\u7684\u7687\u5b50\u662f\u4e2a\u6b8b\u5e9f\uff1f\u6b8b\u5e9f\u6211\u559c\u6b22\uff0c\u4efb\u6211\u62ff\u634f\uff01\u3000\u3000\u4e00\u624b\u533b\u672f\u5999\u624b\u56de\u6625\uff0c\u533b\u597d\u7687\u5b50\u6b8b\u5e9f\u53cc\u817f\uff0c\u539f\u672c\u60f3\u62c9\u7740\u7687\u5b50\u7ed9\u81ea\u5df1\u6491\u8170\uff0c\u7ed3\u679c\u8c01\u60f3\u5230\u8fd9\u4e2a\u7687\u5b50\u7adf\u662f\u4e2a\u8179\u9ed1\u7684\uff01\u3000\u3000\u8c01\u62ff\u634f\u8c01\uff0c\u8fd8\u8bf4\u4e0d\u4e00\u5b9a\u5462\u2026\u2026", "title": "\u6211\u5bb6\u738b\u5983\u662f\u9017\u6bd4", "url": "http://www.17k.com/book/2702194.html", "average": -1.0, "cover": "http://img.17k.com/images/bookcover/partner/21/94/2702194/2702194.jpg", "reviews": 946418, "authors": [{"url": "http://www.17k.com/zuozhe/56805906", "name": "\u5317\u4e5d\u7af9"}], "type": ["\u53e4\u4ee3\u91cd\u751f"], "outlinks": ["http://www.17k.com/book/2794982.html", "http://www.17k.com/book/2801292.html", "http://www.17k.com/book/2816318.html", "http://www.17k.com/book/2797575.html", "http://www.17k.com/book/2802516.html", "http://www.17k.com/book/2812195.html", "http://www.17k.com/book/2820143.html", "http://www.17k.com/book/2807943.html", "http://www.17k.com/book/2813457.html", "http://www.17k.com/book/2798058.html", "http://www.17k.com/book/2815617.html", "http://www.17k.com/book/2805259.html", "http://www.17k.com/book/2760255.html", "http://www.17k.com/book/2686894.html", "http://www.17k.com/book/2797016.html", "http://www.17k.com/book/2767246.html", "http://www.17k.com/book/2764239.html", "http://www.17k.com/book/2754498.html", "http://www.17k.com/book/2754900.html", "http://www.17k.com/book/2625740.html", "http://www.17k.com/book/2213315.html", "http://www.17k.com/book/2402178.html", "http://www.17k.com/book/2691221.html", "http://www.17k.com/book/2210699.html", "http://www.17k.com/book/1797752.html", "http://www.17k.com/book/2575507.html", "http://www.17k.com/book/2705181.html", "http://www.17k.com/book/2702539.html", "http://www.17k.com/book/2474887.html", "http://www.17k.com/book/2674733.html", "http://www.17k.com/book/2822076.html", "http://www.17k.com/book/2809894.html", "http://www.17k.com/book/2822077.html", "http://www.17k.com/book/2811930.html", "http://www.17k.com/book/2815548.html", "http://www.17k.com/book/2819620.html", "http://www.17k.com/book/2809964.html", "http://www.17k.com/book/2808200.html", "http://www.17k.com/book/2820100.html", "http://www.17k.com/book/2822978.html", "http://www.17k.com/book/2804337.html", "http://www.17k.com/book/2798814.html", "http://www.17k.com/book/2785153.html", "http://www.17k.com/book/2731559.html", "http://www.17k.com/book/2722533.html", "http://www.17k.com/book/2458377.html", "http://www.17k.com/book/2743300.html", "http://www.17k.com/book/973809.html", "http://www.17k.com/book/2651367.html", "http://www.17k.com/book/2726194.html", "http://www.17k.com/book/2790214.html", "http://www.17k.com/book/493239.html", "http://www.17k.com/book/108821.html", "http://www.17k.com/book/1398783.html", "http://www.17k.com/book/83528.html", "http://www.17k.com/book/1859126.html", "http://www.17k.com/book/1741975.html", "http://www.17k.com/book/192453.html", "http://www.17k.com/book/2459058.html", "http://www.17k.com/book/1050747.html", "http://www.17k.com/book/2700315.html", "http://www.17k.com/book/2818940.html", "http://www.17k.com/book/2819519.html", "http://www.17k.com/book/2816390.html", "http://www.17k.com/book/2819588.html", "http://www.17k.com/book/2813768.html", "http://www.17k.com/book/2822406.html", "http://www.17k.com/book/2772164.html", "http://www.17k.com/book/2784023.html", "http://www.17k.com/book/2811877.html", "http://www.17k.com/book/2809119.html", "http://www.17k.com/book/2803700.html", "http://www.17k.com/book/2819561.html", "http://www.17k.com/book/2746506.html", "http://www.17k.com/book/2811836.html", "http://www.17k.com/book/2614810.html", "http://www.17k.com/book/1592435.html", "http://www.17k.com/book/1949748.html", "http://www.17k.com/book/2265802.html", "http://www.17k.com/book/2743240.html", "http://www.17k.com/book/2657437.html", "http://www.17k.com/book/2644502.html", "http://www.17k.com/book/2199900.html", "http://www.17k.com/book/2725436.html", "http://www.17k.com/book/2629978.html"]}