{"ratings": -1, "userreviews": [{"userName": "17k\u4e66\u53cbuty1mx979", "userReviewDate": "2018-06-05", "userURL": "http://user.17k.com/62538952", "userReview": "\u8fd9\u7bc7\u6587\u662f\u5f88\u4e45\u4ee5\u524d\u770b\u7684\u3002\u7b2c\u4e00\u7bc7\u8d77\u5927\u65e9\u722c\u8d77\u6765\u770b\u7684\u5c0f\u8bf4\u3002"}, {"userName": "17k\u4e66\u53cbuty1mx979", "userReviewDate": "2018-06-05", "userURL": "http://user.17k.com/62538952", "userReview": "[\u6253\u8d4f]\u6211\u6253\u8d4f\u4e861\u4e2a'\u5c0f\u5fc3\u5fc3'\uff01\uff01"}, {"userName": "\u6ee1\u5929\u7e41\u661f\u4e0d\u53ca\u56de\u7738", "userReviewDate": "2018-04-06", "userURL": "http://user.17k.com/60269847", "userReview": "&nbsp; \u8fd9\u540d\u5b57\u6211\u7ed9\u6ee1\u5206\uff01\u256e(\u256f\u25bd\u2570)\u256d"}, {"userName": "\u6ca1\u6709\u59b9\u59b9\u7684\u59b9\u63a7", "userReviewDate": "2018-03-08", "userURL": "http://user.17k.com/60314556", "userReview": "\u65b0\u4eba\u5c0f\u8bf4<a target='_blank' href='http://www.17k.com/book/2790062.html'>\u300a\u751f\u547d\u5f02\u6b21\u5143\u300b</a>\u4e32\u95e8\u3002\u9001\u4e0a\u795d\u798f\uff0c\u652f\u6301\u5927\u4f5c\u3002"}, {"userName": "\u7834\u7a7a\u4e4b\u4e0b", "userReviewDate": "2018-02-09", "userURL": "http://user.17k.com/59582334", "userReview": "<a target='_blank' href='http://www.17k.com/book/2766027.html'>\u300a\u7cbe\u7075\u5b9d\u53ef\u68a6\uff1a\u4e16\u754c\u7684\u5dc5\u5cf0\u300b</a>\u524d\u6765\u62dc\u8bbf"}, {"userName": "kool\u6377", "userReviewDate": "2018-01-31", "userURL": "http://user.17k.com/56730892", "userReview": "\u63a8\u8350\u4e00\u672c\u597d\u770b\u7684\u4e66<a target='_blank' href='http://www.17k.com/book/2551937.html'>\u300a\u8d85\u65b0\u4eba\u300b</a>\uff0c\u60ca\u9669\u523a\u6fc0\uff0c\u6696\u6627\u6d6a\u6f2b\u4e0d\u65ad\uff0c\u5929\u5929\u66f4\u65b0\uff0c\u591a\u591a\u652f\u6301\uff0c\u6765\u4e2a\u6536\u85cf\u3002\u70b9\u51fb\u4e66\u540d\u5c31\u53ef\u4ee5\u770b\u5230\u4e66\u4e86\u3002"}, {"userName": "\u6708\u843d\u68a6\u8ffd\u5fc6", "userReviewDate": "2017-10-22", "userURL": "http://user.17k.com/57478135", "userReview": "\u643a<a target='_blank' href='http://www.17k.com/book/2660764.html'>\u300a\u5341\u6708\u8840\u6a31\u59d7\u59d7\u76db\u653e\u300b</a>\u6765\u5b66\u4e60\uff0c\u67ef\u5357\u5165\u5751\uff0c\u4eca\u65e5\u4ecd\u604b\u3002"}, {"userName": "qzuser542975691", "userReviewDate": "2017-10-09", "userURL": "http://user.17k.com/57857509", "userReview": "\u597d\u597d\u770b\uff0c\u4e0d\u9519\uff0c\u6211\u5f88\u559c\u6b22\u3002"}, {"userName": "17K\u4e66\u53cbrp9l8qpq", "userReviewDate": "2017-08-16", "userURL": "http://user.17k.com/56943429", "userReview": "\u4e0d\u9519 \u597d\u770b"}, {"userName": "\u6c5f\u6615\u5170", "userReviewDate": "2017-08-16", "userURL": "http://user.17k.com/46082731", "userReview": "\u8fd9\u7bc7\u6587\u5f88\u4e45\u4e4b\u524d\u90fd\u6709\u4e86\u554a\u3002\u3002\u3002\u6211\u90fd\u770b\u5b8c\u4e86.........\u7ed3\u5c40\u90fd\u6709\u4e86........"}, {"userName": "\u5929\u771f\uff3f\u2121\u5c11\u5e74578797620", "userReviewDate": "2017-08-12", "userURL": "http://user.17k.com/56874771", "userReview": "\u4e3a\u4ec0\u4e48\u91cc\u9762\u6807\u70b9\u7b26\u53f7\u770b\u4e0d\u61c2\uff0c\u5c0f\u5b66\u6bd5\u4e1a\u4e86\u4e48"}, {"userName": "\u6d45\u590f\u827a\u51c9", "userReviewDate": "2017-08-10", "userURL": "http://user.17k.com/56695105", "userReview": "\u643a<a target='_blank' href='http://www.17k.com/book/2606063.html'>\u300a\u7f51\u738b\u4e4b\u6700\u5f3a\u738b\u8005\u300b</a>\u6765\u8bbf\uff0c\u671b\u5927\u5927\u56de\u8bbf\u6307\u5bfc"}, {"userName": "\u76d6\u4e16\u82f1\u96c4\u548c\u7d2b\u971e", "userReviewDate": "2017-07-23", "userURL": "http://user.17k.com/56529650", "userReview": "\u5f88\u597d\u770b\u54e6<a target='_blank' href='http://user.17k.com/32218137'>@\u6c5f\u6237\u5ddd\u67ef\u5357\u548c\u57fa\u5fb7</a>"}, {"userName": "\u4e00\u6735\u6619\u82b1\u4e00\u6735\u4e91\ufe4f\u2609\u30df502761888", "userReviewDate": "2017-07-02", "userURL": "http://user.17k.com/56024571", "userReview": "\u600e\u4e48\u4e0d\u66f4\u65b0\u4e86\uff01&#55357;&#56865;&#55357;&#56865;&#55357;&#56865;&#55357;&#56865;&#55357;&#56865;&#55357;&#56865;&#55357;&#56865;&#55357;&#56865;&#55357;&#56865;&#55357;&#56865;&#55357;&#56865;&#55357;&#56865;&#55357;&#56865;&#55357;&#56865;&#55357;&#56865;&#55357;&#56865;&#55357;&#56865;&#55357;&#56865;&#..."}, {"userName": "\u521d\u5fc3\u672a\u5c3d", "userReviewDate": "2017-03-26", "userURL": "http://user.17k.com/52668268", "userReview": "\u5389\u5bb3\uff0c\u6562\u95ee\u4f5c\u8005\u5927\u5927\u80fd\u770b\u770b\u6211\u7684\u6587\u5417\uff1f<a target='_blank' href='http://www.17k.com/book/2382103.html'>\u300a\u5e1d\u738b\u7684\u50b2\u5a07\u516c\u4e3b\u300b</a><a target='_blank' href='http://www.17k.com/book/1437938.html'>\u300a\u5973\u914d\u4e0d\u597d\u5f53\u300b</a><a target='_blank' href='http://www.17k.com/book/2419390.html'>\u300a\u5b88\u62a4\u751c\u5fc3\u4e4b\u6a31\u82b1\u822c\u7684\u68a6\u300b</a>"}, {"userName": "\u9752\u6da9\u5e74\u534e961852953", "userReviewDate": "2017-03-14", "userURL": "http://user.17k.com/54148572", "userReview": "\u653e\u5c41"}, {"userName": "\u8001\u5b85\u91cc\u7684\u732b", "userReviewDate": "2017-01-31", "userURL": "http://user.17k.com/46005645", "userReview": "\u8fd9\u672c\u4e66\u4e0d\u662f\u8bfb\u8bfb\u7684\u5417\u2026\u65e9\u90fd\u5b8c\u7ed3\u4e86\u2026\u8fd9\u662f\u76d7\u6587\uff1f\u5185\u5bb9\u4e00\u6a21\u4e00\u6837\uff0c\u76ee\u5f55\u6bcf\u7ae0\u6807\u9898\u90fd\u6539\u4e86"}, {"userName": "Menhera\u9171", "userReviewDate": "2017-01-29", "userURL": "http://user.17k.com/51959524", "userReview": "\u597d\u559c\u6b22\u8fd9\u7bc7\u6587\u6587\uff08\u5176\u5b9e\u6211\u7b2c\u4e00\u6b21\u676517k\u770b\u7684\u5c31\u662f\u8fd9\u7bc7\u5c0f\u8bf4\uff0c\u867d\u7136\u6211\u5230\u73b0\u5728\u624d\u8bc4\u8bba\u3010\u6342\u8138\u3011\uff09"}, {"userName": "\u6a31\u4f9d\u96ea\u6f9c", "userReviewDate": "2017-01-21", "userURL": "http://user.17k.com/48683944", "userReview": "\u6211\u662f\u67ef\u54c0\u515a\u3002\u3002\u3002\u3002\u3002\u3002"}, {"userName": "Top\u4e36\u5f6a\u608d\u4e3f624372106", "userReviewDate": "2016-12-28", "userURL": "http://user.17k.com/52115882", "userReview": "\u643a\u3010\u67ef\u5357\u4e4b\u8d85\u795e\u7cfb\u7edf\u3011\u6765\u8bbf \u5e0c\u671b\u559c\u6b22"}], "description": "\u67ef\u5357\uff0c\u7b49\u4e86\u65b0\u4e00\u8fd9\u4e48\u591a\u5e74\u6211\u7ec8\u4e8e\u653e\u5f03\u4e86\uff0c\u56e0\u4e3a\uff0c\u4ed6\u5e76\u6ca1\u6709\u51fa\u73b0\u8fc7\u8ddf\u6211\u544a\u767d\uff0c\u4e45\u800c\u4e45\u4e4b\uff0c\u6211\u4fbf\u7231\u4e0a\u4e86\u4f60\u67ef\u5357\u5bf9\u4e0d\u8d77\uff0c\u65b0\u4e00\u539f\u8c05\u6211\u7231\u4e0a\u67ef\u5357\u3002\u3000\u3000\u60f3\u770b\u602a\u76d7\u57fa\u5fb7\u534e\u4e3d\u7684\u8f6c\u8eab\u5417\uff1f\u3000\u3000\u60f3\u77e5\u9053\u67ef\u5357\u7684\u611f\u60c5\u5f52\u5c5e\u5417\uff1f\u3000\u3000\u60f3\u77e5\u9053\u7ec4\u7ec7\u7684boss\u662f\u4f55\u4eba\u5417\uff1f\u3000\u3000\u60f3\u77e5\u9053\u7ec4\u7ec7\u7684\u6700\u7ec8\u76ee\u7684\u5417\uff1f\u3000\u3000\u66f2\u6298\u7684\u6545\u4e8b\u5c06\u4f1a\u600e\u6837\u53d1\u5c55\u8bf7\u9501\u5b9a\u300a\u65b0\u4e00\u539f\u8c05\u6211\u7231\u4e0a\u67ef\u5357\u300b\u4e00\u5207\u8c1c\u9898\uff0c\u5c31\u6b64\u89e3\u5f00......", "title": "\u65b0\u4e00\u539f\u8c05\u6211\u7231\u4e0a\u4e86\u67ef\u5357", "url": "http://www.17k.com/book/680645.html", "average": -1.0, "cover": "http://img.17k.com/images/bookcover/2013/3403/17/680645-1382265394000.jpg", "reviews": 2133950, "authors": [{"url": "http://www.17k.com/zuozhe/32218137", "name": "\u67ef\u5357\u662f\u4fa6\u63a2"}], "type": ["\u52a8\u6f2b\u540c\u4eba"], "outlinks": ["http://www.17k.com/book/2794982.html", "http://www.17k.com/book/2801292.html", "http://www.17k.com/book/2816318.html", "http://www.17k.com/book/2797575.html", "http://www.17k.com/book/2802516.html", "http://www.17k.com/book/2812195.html", "http://www.17k.com/book/2820143.html", "http://www.17k.com/book/2807943.html", "http://www.17k.com/book/2813457.html", "http://www.17k.com/book/2798058.html", "http://www.17k.com/book/2815617.html", "http://www.17k.com/book/2805259.html", "http://www.17k.com/book/2760255.html", "http://www.17k.com/book/2686894.html", "http://www.17k.com/book/2797016.html", "http://www.17k.com/book/2767246.html", "http://www.17k.com/book/2764239.html", "http://www.17k.com/book/2754498.html", "http://www.17k.com/book/2754900.html", "http://www.17k.com/book/2625740.html", "http://www.17k.com/book/2213315.html", "http://www.17k.com/book/2402178.html", "http://www.17k.com/book/2691221.html", "http://www.17k.com/book/2210699.html", "http://www.17k.com/book/1797752.html", "http://www.17k.com/book/2575507.html", "http://www.17k.com/book/2705181.html", "http://www.17k.com/book/2702539.html", "http://www.17k.com/book/2474887.html", "http://www.17k.com/book/2674733.html", "http://www.17k.com/book/2822076.html", "http://www.17k.com/book/2809894.html", "http://www.17k.com/book/2822077.html", "http://www.17k.com/book/2811930.html", "http://www.17k.com/book/2815548.html", "http://www.17k.com/book/2819620.html", "http://www.17k.com/book/2809964.html", "http://www.17k.com/book/2808200.html", "http://www.17k.com/book/2820100.html", "http://www.17k.com/book/2822978.html", "http://www.17k.com/book/2804337.html", "http://www.17k.com/book/2798814.html", "http://www.17k.com/book/2785153.html", "http://www.17k.com/book/2731559.html", "http://www.17k.com/book/2722533.html", "http://www.17k.com/book/2458377.html", "http://www.17k.com/book/2743300.html", "http://www.17k.com/book/973809.html", "http://www.17k.com/book/2651367.html", "http://www.17k.com/book/2726194.html", "http://www.17k.com/book/2790214.html", "http://www.17k.com/book/493239.html", "http://www.17k.com/book/108821.html", "http://www.17k.com/book/1398783.html", "http://www.17k.com/book/83528.html", "http://www.17k.com/book/1859126.html", "http://www.17k.com/book/1741975.html", "http://www.17k.com/book/192453.html", "http://www.17k.com/book/2459058.html", "http://www.17k.com/book/1050747.html", "http://www.17k.com/book/2700315.html", "http://www.17k.com/book/2818940.html", "http://www.17k.com/book/2819519.html", "http://www.17k.com/book/2816390.html", "http://www.17k.com/book/2819588.html", "http://www.17k.com/book/2813768.html", "http://www.17k.com/book/2822406.html", "http://www.17k.com/book/2772164.html", "http://www.17k.com/book/2784023.html", "http://www.17k.com/book/2811877.html", "http://www.17k.com/book/2809119.html", "http://www.17k.com/book/2803700.html", "http://www.17k.com/book/2819561.html", "http://www.17k.com/book/2746506.html", "http://www.17k.com/book/2811836.html", "http://www.17k.com/book/2614810.html", "http://www.17k.com/book/1592435.html", "http://www.17k.com/book/1949748.html", "http://www.17k.com/book/2265802.html", "http://www.17k.com/book/2743240.html", "http://www.17k.com/book/2657437.html", "http://www.17k.com/book/2644502.html", "http://www.17k.com/book/2199900.html", "http://www.17k.com/book/2725436.html", "http://www.17k.com/book/2629978.html"]}