{"ratings": -1, "userreviews": [], "description": "\u4ed6\u662f\u5927\u5b8b\u7b2c\u4e00\u624d\u5b50\uff0c\u60ca\u8273\u4e86\u6211\u521d\u5f00\u7684\u60c5\u7aa6\u3002\u4ee5\u4e3a\u53ef\u4ee5\u4e3e\u6848\u9f50\u7709\uff0c\u8c01\u77e5\u5a5a\u540e\u5c0f\u4eba\u6311\u62e8\uff0c\u5a46\u5a46\u6076\u6bd2\uff0c\u4f24\u6211\u4f53\u65e0\u5b8c\u80a4\u3002\u4ed6\u88ab\u9769\u53bb\u529f\u540d\uff0c\u6c38\u4e16\u4e0d\u5f97\u5165\u4ed5\uff0c\u843d\u5f97\u75c5\u6b7b\u821f\u4e2d\u3002\u59d0\u59d0\u4e5f\u88ab\u91d1\u4eba\u7ed1\u67b6\uff0c\u751f\u6b7b\u672a\u535c\u3002\u7231\u90ce\u75c5\u901d\uff0c\u6211\u5fc3\u5982\u6b7b\u7070\uff0c\u672c\u60f3\u968f\u4ed6\u53bb\u4e86\uff0c\u8fd9\u65f6\uff0c\u53e6\u4e00\u4e2a\u7537\u4eba\uff0c\u8d70\u8fdb\u4e86\u6211\u7684\u751f\u547d\uff0c\u4ed6\u8bf4\uff0c\u5373\u4f7f\u5927\u5b8b\u53ea\u80fd\u6709\u4e00\u4e2a\u7687\u540e\uff0c\u4e5f\u8981\u6211\u7a7f\u7740\u7687\u540e\u7684\u670d\u5236\u4e0b\u846c\u00b7\u00b7\u00b7\u00b7\u00b7\u00b7", "title": "\u6e29\u6210\u7687\u540e\u4f20\u5947", "url": "http://www.17k.com/book/2836426.html", "average": -1.0, "cover": "http://img.17k.com/images/bookcover/default_cover1.jpg", "reviews": 98, "authors": [{"url": "http://www.17k.com/zuozhe/62614795", "name": "\u5fc6\u6148\u5c45\u58eb"}], "type": ["\u5bab\u5ef7\u8d35\u65cf"], "outlinks": ["http://www.17k.com/book/2794982.html", "http://www.17k.com/book/2801292.html", "http://www.17k.com/book/2816318.html", "http://www.17k.com/book/2797575.html", "http://www.17k.com/book/2802516.html", "http://www.17k.com/book/2812195.html", "http://www.17k.com/book/2820143.html", "http://www.17k.com/book/2807943.html", "http://www.17k.com/book/2813457.html", "http://www.17k.com/book/2798058.html", "http://www.17k.com/book/2815617.html", "http://www.17k.com/book/2805259.html", "http://www.17k.com/book/2760255.html", "http://www.17k.com/book/2686894.html", "http://www.17k.com/book/2797016.html", "http://www.17k.com/book/2767246.html", "http://www.17k.com/book/2764239.html", "http://www.17k.com/book/2754498.html", "http://www.17k.com/book/2754900.html", "http://www.17k.com/book/2625740.html", "http://www.17k.com/book/2213315.html", "http://www.17k.com/book/2402178.html", "http://www.17k.com/book/2691221.html", "http://www.17k.com/book/2210699.html", "http://www.17k.com/book/1797752.html", "http://www.17k.com/book/2575507.html", "http://www.17k.com/book/2705181.html", "http://www.17k.com/book/2702539.html", "http://www.17k.com/book/2474887.html", "http://www.17k.com/book/2674733.html", "http://www.17k.com/book/2822076.html", "http://www.17k.com/book/2809894.html", "http://www.17k.com/book/2822077.html", "http://www.17k.com/book/2811930.html", "http://www.17k.com/book/2815548.html", "http://www.17k.com/book/2819620.html", "http://www.17k.com/book/2809964.html", "http://www.17k.com/book/2808200.html", "http://www.17k.com/book/2820100.html", "http://www.17k.com/book/2822978.html", "http://www.17k.com/book/2804337.html", "http://www.17k.com/book/2798814.html", "http://www.17k.com/book/2785153.html", "http://www.17k.com/book/2731559.html", "http://www.17k.com/book/2722533.html", "http://www.17k.com/book/2458377.html", "http://www.17k.com/book/2743300.html", "http://www.17k.com/book/973809.html", "http://www.17k.com/book/2651367.html", "http://www.17k.com/book/2726194.html", "http://www.17k.com/book/2790214.html", "http://www.17k.com/book/493239.html", "http://www.17k.com/book/108821.html", "http://www.17k.com/book/1398783.html", "http://www.17k.com/book/83528.html", "http://www.17k.com/book/1859126.html", "http://www.17k.com/book/1741975.html", "http://www.17k.com/book/192453.html", "http://www.17k.com/book/2459058.html", "http://www.17k.com/book/1050747.html", "http://www.17k.com/book/2700315.html", "http://www.17k.com/book/2818940.html", "http://www.17k.com/book/2819519.html", "http://www.17k.com/book/2816390.html", "http://www.17k.com/book/2819588.html", "http://www.17k.com/book/2813768.html", "http://www.17k.com/book/2822406.html", "http://www.17k.com/book/2772164.html", "http://www.17k.com/book/2784023.html", "http://www.17k.com/book/2811877.html", "http://www.17k.com/book/2809119.html", "http://www.17k.com/book/2803700.html", "http://www.17k.com/book/2819561.html", "http://www.17k.com/book/2746506.html", "http://www.17k.com/book/2811836.html", "http://www.17k.com/book/2614810.html", "http://www.17k.com/book/1592435.html", "http://www.17k.com/book/1949748.html", "http://www.17k.com/book/2265802.html", "http://www.17k.com/book/2743240.html", "http://www.17k.com/book/2657437.html", "http://www.17k.com/book/2644502.html", "http://www.17k.com/book/2199900.html", "http://www.17k.com/book/2725436.html", "http://www.17k.com/book/2629978.html"]}