{"ratings": -1, "userreviews": [{"userName": "\u9ec4\u74dc\u7684\u5bbf\u547d", "userReviewDate": "2018-02-10", "userURL": "http://user.17k.com/53195742", "userReview": "<a target='_blank' href='http://www.17k.com/book/2377865.html'>\u300a\u81f3\u9738\u82cd\u751f\u8bc0\u300b</a>\u6765\u8bbf\uff0c\u6c42\u652f\u6301\u6c42\u6269\u6563\uff0c\u87f9\u87f9\u3002"}], "description": "\u8c0b\u6740\u4eb2\u592b\u3001\u754f\u7f6a\u670d\u6bd2\u2014\u2014\u82cf\u65d6\u666f\u7684\u4eba\u751f\uff0c\u5c31\u6b64\u60e8\u6de1\u843d\u5e55\u3002\u3000\u3000\u7686\u56e0\u5f97\u4e0d\u8bc6\u597d\u6b79\u3001\u53c8\u9047\u90a3\u201c\u5982\u610f\u72fc\u541b\u201d\u2014\u2014\u5374\u5e78\u80fd\u8c46\u853b\u91cd\u751f\u3002\u3000\u3000\u53d1\u8a93\u8131\u80ce\u6362\u9aa8\u3001\u534e\u4e3d\u8f6c\u8eab\u2014\u2014\u4e14\u770b\u95fa\u9601\u5343\u91d1\uff0c\u5982\u4f55\u706d\u5201\u5974\u3001\u6597\u201c\u72fc\u201d\u541b\u3001\u626d\u4e7e\u5764\u3002\u3000\u3000\u6b63\u6b65\u6b65\u4e3a\u8425\uff0c\u53c8\u5ffd\u800c\u53d1\u73b0\u2014\u2014\u4f3c\u4e4e\u6709\u4eba\u4e0e\u5979\u6709\u76f8\u540c\u7684\u7ecf\u5386\u2026\u2026\u3000\u3000\u67d0\u82cf\u53ef\u601c\u516e\u516e\uff1a\u8be5\u8fd8\u7684\u6211\u90fd\u8fd8\u4e86\uff0c\u592b\u541b\u5c1a\u5f85\u5982\u4f55\uff1f\u3000\u3000\u67d0\u865e\u6311\u7709\u659c\u7768\uff1a\u662f\u5417\uff0c\u4e3a\u592b\u600e\u4e48\u89c9\u5f97\u8fd8\u8fdc\u8fdc\u4e0d\u591f\uff1f", "title": "\u91cd\u751f\u4e4b\u518d\u8bb8\u82b3\u534e", "url": "http://www.17k.com/book/2697157.html", "average": -1.0, "cover": "http://img.17k.com/images/bookcover/partner/71/57/2697157/2697157.jpg", "reviews": 21498, "authors": [{"url": "http://www.17k.com/zuozhe/56805591", "name": "\u5239\u65f6\u7ea2\u7626"}], "type": ["\u53e4\u4ee3\u91cd\u751f"], "outlinks": ["http://www.17k.com/book/2794982.html", "http://www.17k.com/book/2801292.html", "http://www.17k.com/book/2816318.html", "http://www.17k.com/book/2797575.html", "http://www.17k.com/book/2802516.html", "http://www.17k.com/book/2812195.html", "http://www.17k.com/book/2820143.html", "http://www.17k.com/book/2807943.html", "http://www.17k.com/book/2813457.html", "http://www.17k.com/book/2798058.html", "http://www.17k.com/book/2815617.html", "http://www.17k.com/book/2805259.html", "http://www.17k.com/book/2760255.html", "http://www.17k.com/book/2686894.html", "http://www.17k.com/book/2797016.html", "http://www.17k.com/book/2767246.html", "http://www.17k.com/book/2764239.html", "http://www.17k.com/book/2754498.html", "http://www.17k.com/book/2754900.html", "http://www.17k.com/book/2625740.html", "http://www.17k.com/book/2213315.html", "http://www.17k.com/book/2402178.html", "http://www.17k.com/book/2691221.html", "http://www.17k.com/book/2210699.html", "http://www.17k.com/book/1797752.html", "http://www.17k.com/book/2575507.html", "http://www.17k.com/book/2705181.html", "http://www.17k.com/book/2702539.html", "http://www.17k.com/book/2474887.html", "http://www.17k.com/book/2674733.html", "http://www.17k.com/book/2822076.html", "http://www.17k.com/book/2809894.html", "http://www.17k.com/book/2822077.html", "http://www.17k.com/book/2811930.html", "http://www.17k.com/book/2815548.html", "http://www.17k.com/book/2819620.html", "http://www.17k.com/book/2809964.html", "http://www.17k.com/book/2808200.html", "http://www.17k.com/book/2820100.html", "http://www.17k.com/book/2822978.html", "http://www.17k.com/book/2804337.html", "http://www.17k.com/book/2798814.html", "http://www.17k.com/book/2785153.html", "http://www.17k.com/book/2731559.html", "http://www.17k.com/book/2722533.html", "http://www.17k.com/book/2458377.html", "http://www.17k.com/book/2743300.html", "http://www.17k.com/book/973809.html", "http://www.17k.com/book/2651367.html", "http://www.17k.com/book/2726194.html", "http://www.17k.com/book/2790214.html", "http://www.17k.com/book/493239.html", "http://www.17k.com/book/108821.html", "http://www.17k.com/book/1398783.html", "http://www.17k.com/book/83528.html", "http://www.17k.com/book/1859126.html", "http://www.17k.com/book/1741975.html", "http://www.17k.com/book/192453.html", "http://www.17k.com/book/2459058.html", "http://www.17k.com/book/1050747.html", "http://www.17k.com/book/2700315.html", "http://www.17k.com/book/2818940.html", "http://www.17k.com/book/2819519.html", "http://www.17k.com/book/2816390.html", "http://www.17k.com/book/2819588.html", "http://www.17k.com/book/2813768.html", "http://www.17k.com/book/2822406.html", "http://www.17k.com/book/2772164.html", "http://www.17k.com/book/2784023.html", "http://www.17k.com/book/2811877.html", "http://www.17k.com/book/2809119.html", "http://www.17k.com/book/2803700.html", "http://www.17k.com/book/2819561.html", "http://www.17k.com/book/2746506.html", "http://www.17k.com/book/2811836.html", "http://www.17k.com/book/2614810.html", "http://www.17k.com/book/1592435.html", "http://www.17k.com/book/1949748.html", "http://www.17k.com/book/2265802.html", "http://www.17k.com/book/2743240.html", "http://www.17k.com/book/2657437.html", "http://www.17k.com/book/2644502.html", "http://www.17k.com/book/2199900.html", "http://www.17k.com/book/2725436.html", "http://www.17k.com/book/2629978.html"]}